spotdl_gui/__init__.py
spotdl_gui/main.py
spotdl_gui-0.2.1.dist-info/licenses/LICENSE
spotdl_gui-0.2.1.dist-info/METADATA
spotdl_gui-0.2.1.dist-info/WHEEL
spotdl_gui-0.2.1.dist-info/entry_points.txt
spotdl_gui-0.2.1.dist-info/top_level.txt
spotdl_gui-0.2.1.dist-info/RECORD
