Metadata-Version: 2.4
Name: spotdl_gui
Version: 0.2.1
Summary: A user-friendly GUI for spotdl to download Spotify music
Author-email: Ye8ibp0oAa <Ye8ibp0oAa@proton.me>
License:                     GNU GENERAL PUBLIC LICENSE
Project-URL: Homepage, https://github.com/Ye8ibp0oAa/spotdl_gui
Keywords: spotify,downloader,music,audio,gui
Classifier: Programming Language :: Python :: 3
Classifier: License :: OSI Approved :: GNU General Public License v3 or later (GPLv3+)
Classifier: Operating System :: OS Independent
Classifier: Development Status :: 4 - Beta
Classifier: Intended Audience :: End Users/Desktop
Classifier: Topic :: Multimedia :: Sound/Audio
Requires-Python: >=3.10
License-File: LICENSE
Requires-Dist: PyQt5>=5.15
Requires-Dist: spotdl>=4.4.2
Dynamic: license-file
